octo_pipeline_python/__init__.py
octo_pipeline_python/octo.py
octo_pipeline_python/actions/__init__.py
octo_pipeline_python/actions/action.py
octo_pipeline_python/actions/action_result.py
octo_pipeline_python/actions/action_settings.py
octo_pipeline_python/actions/action_type.py
octo_pipeline_python/backends/__init__.py
octo_pipeline_python/backends/backend.py
octo_pipeline_python/backends/backend_auth_details.py
octo_pipeline_python/backends/backend_description.py
octo_pipeline_python/backends/backend_settings.py
octo_pipeline_python/backends/backends.py
octo_pipeline_python/backends/backends_context.py
octo_pipeline_python/backends/backends_database.py
octo_pipeline_python/backends/backends_keyring.py
octo_pipeline_python/commands/__init__.py
octo_pipeline_python/commands/backends_command.py
octo_pipeline_python/commands/command.py
octo_pipeline_python/commands/pipeline_command.py
octo_pipeline_python/commands/workspace_command.py
octo_pipeline_python/common/__init__.py
octo_pipeline_python/common/database.py
octo_pipeline_python/common/surrounding.py
octo_pipeline_python/pipeline/__init__.py
octo_pipeline_python/pipeline/pipeline.py
octo_pipeline_python/pipeline/pipeline_action.py
octo_pipeline_python/pipeline/pipeline_builder.py
octo_pipeline_python/pipeline/pipeline_context.py
octo_pipeline_python/pipeline/pipeline_database.py
octo_pipeline_python/pipeline/pipeline_description.py
octo_pipeline_python/utils/__init__.py
octo_pipeline_python/utils/exec.py
octo_pipeline_python/utils/git.py
octo_pipeline_python/utils/logger.py
octo_pipeline_python/utils/pydantic_argparse.py
octo_pipeline_python/utils/search.py
octo_pipeline_python/workspace/__init__.py
octo_pipeline_python/workspace/workspace.py
octo_pipeline_python/workspace/workspace_builder.py
octo_pipeline_python/workspace/workspace_context.py
octo_pipeline_python/workspace/workspace_database.py
octo_pipeline_python/workspace/workspace_description.py
octo_pipeline_python/workspace/workspace_pipeline.py
octo_pipeline_python-1.3.2.dist-info/LICENSE.txt
octo_pipeline_python-1.3.2.dist-info/METADATA
octo_pipeline_python-1.3.2.dist-info/README.md
octo_pipeline_python-1.3.2.dist-info/WHEEL
octo_pipeline_python-1.3.2.dist-info/entry_points.txt
octo_pipeline_python-1.3.2.dist-info/top_level.txt
octo_pipeline_python-1.3.2.dist-info/RECORD
