Metadata-Version: 2.1
Name: octo-pipeline-python
Version: 1.3.2
Summary: Octo pipeline
Home-page: https://github.com/ofiriluz/octo-pipeline-python
Author: Ofir Iluz
Author-email: iluzofir@gmail.com
License: MIT
Classifier: Intended Audience :: Developers
Classifier: Natural Language :: English
Classifier: Programming Language :: Python
Classifier: Programming Language :: Python :: 3.11
Classifier: Programming Language :: Python :: 3.12
Requires-Python: >= 3.11
License-File: LICENSE.txt
License-File: README.md
Requires-Dist: requests
Requires-Dist: colorama
Requires-Dist: pydantic
Requires-Dist: packaging
Requires-Dist: argcomplete
Requires-Dist: GitPython
Requires-Dist: pyyaml==5.3.1
Requires-Dist: toml
Requires-Dist: overrides
Requires-Dist: networkx
Requires-Dist: keyring
Requires-Dist: python-dateutil
Requires-Dist: keyrings.cryptfile
Provides-Extra: blackduck
Requires-Dist: octo-pipeline-backend-blackduck-python; extra == "blackduck"
Provides-Extra: cdk
Requires-Dist: octo-pipeline-backend-cdk-python; extra == "cdk"
Provides-Extra: yaml
Requires-Dist: octo-pipeline-backend-yaml-python; extra == "yaml"
Provides-Extra: ansible
Requires-Dist: octo-pipeline-backend-ansible-python; extra == "ansible"
Provides-Extra: gpg
Requires-Dist: octo-pipeline-backend-gpg-python; extra == "gpg"
Provides-Extra: setuptools
Requires-Dist: octo-pipeline-backend-setuptools-python; extra == "setuptools"
Provides-Extra: cppcheck
Requires-Dist: octo-pipeline-backend-cppcheck-python; extra == "cppcheck"
Provides-Extra: snyk
Requires-Dist: octo-pipeline-backend-snyk-python; extra == "snyk"
Provides-Extra: perl
Requires-Dist: octo-pipeline-backend-perl-python; extra == "perl"
Provides-Extra: file
Requires-Dist: octo-pipeline-backend-file-python; extra == "file"
Provides-Extra: tar
Requires-Dist: octo-pipeline-backend-tar-python; extra == "tar"
Provides-Extra: pipenv
Requires-Dist: octo-pipeline-backend-pipenv-python; extra == "pipenv"
Provides-Extra: clang
Requires-Dist: octo-pipeline-backend-clang-python; extra == "clang"
Provides-Extra: docker
Requires-Dist: octo-pipeline-backend-docker-python; extra == "docker"
Provides-Extra: conan
Requires-Dist: octo-pipeline-backend-conan-python; extra == "conan"
Provides-Extra: cfn-nag
Requires-Dist: octo-pipeline-backend-cfn-nag-python; extra == "cfn-nag"
Provides-Extra: git
Requires-Dist: octo-pipeline-backend-git-python; extra == "git"
Provides-Extra: pytest
Requires-Dist: octo-pipeline-backend-pytest-python; extra == "pytest"
Provides-Extra: patch
Requires-Dist: octo-pipeline-backend-patch-python; extra == "patch"
Provides-Extra: golang
Requires-Dist: octo-pipeline-backend-golang-python; extra == "golang"
Provides-Extra: s3
Requires-Dist: octo-pipeline-backend-s3-python; extra == "s3"
Provides-Extra: all
Requires-Dist: octo-pipeline-backend-blackduck-python; extra == "all"
Requires-Dist: octo-pipeline-backend-cdk-python; extra == "all"
Requires-Dist: octo-pipeline-backend-yaml-python; extra == "all"
Requires-Dist: octo-pipeline-backend-ansible-python; extra == "all"
Requires-Dist: octo-pipeline-backend-gpg-python; extra == "all"
Requires-Dist: octo-pipeline-backend-setuptools-python; extra == "all"
Requires-Dist: octo-pipeline-backend-cppcheck-python; extra == "all"
Requires-Dist: octo-pipeline-backend-snyk-python; extra == "all"
Requires-Dist: octo-pipeline-backend-perl-python; extra == "all"
Requires-Dist: octo-pipeline-backend-file-python; extra == "all"
Requires-Dist: octo-pipeline-backend-tar-python; extra == "all"
Requires-Dist: octo-pipeline-backend-pipenv-python; extra == "all"
Requires-Dist: octo-pipeline-backend-clang-python; extra == "all"
Requires-Dist: octo-pipeline-backend-docker-python; extra == "all"
Requires-Dist: octo-pipeline-backend-conan-python; extra == "all"
Requires-Dist: octo-pipeline-backend-cfn-nag-python; extra == "all"
Requires-Dist: octo-pipeline-backend-git-python; extra == "all"
Requires-Dist: octo-pipeline-backend-pytest-python; extra == "all"
Requires-Dist: octo-pipeline-backend-patch-python; extra == "all"
Requires-Dist: octo-pipeline-backend-golang-python; extra == "all"
Requires-Dist: octo-pipeline-backend-s3-python; extra == "all"
Provides-Extra: orchestration
Requires-Dist: octo-pipeline-backend-ansible-python; extra == "orchestration"
Requires-Dist: octo-pipeline-backend-yaml-python; extra == "orchestration"
Provides-Extra: security
Requires-Dist: octo-pipeline-backend-blackduck-python; extra == "security"
Requires-Dist: octo-pipeline-backend-cfn-nag-python; extra == "security"
Requires-Dist: octo-pipeline-backend-gpg-python; extra == "security"
Requires-Dist: octo-pipeline-backend-snyk-python; extra == "security"
Provides-Extra: cpp
Requires-Dist: octo-pipeline-backend-blackduck-python; extra == "cpp"
Requires-Dist: octo-pipeline-backend-clang-python; extra == "cpp"
Requires-Dist: octo-pipeline-backend-conan-python; extra == "cpp"
Requires-Dist: octo-pipeline-backend-cppcheck-python; extra == "cpp"
Requires-Dist: octo-pipeline-backend-patch-python; extra == "cpp"
Requires-Dist: octo-pipeline-backend-setuptools-python; extra == "cpp"
Provides-Extra: python
Requires-Dist: octo-pipeline-backend-cdk-python; extra == "python"
Requires-Dist: octo-pipeline-backend-cfn-nag-python; extra == "python"
Requires-Dist: octo-pipeline-backend-pipenv-python; extra == "python"
Requires-Dist: octo-pipeline-backend-pytest-python; extra == "python"
Requires-Dist: octo-pipeline-backend-setuptools-python; extra == "python"
Requires-Dist: octo-pipeline-backend-snyk-python; extra == "python"
Provides-Extra: service
Requires-Dist: octo-pipeline-backend-cdk-python; extra == "service"
Requires-Dist: octo-pipeline-backend-cfn-nag-python; extra == "service"
Requires-Dist: octo-pipeline-backend-pipenv-python; extra == "service"
Requires-Dist: octo-pipeline-backend-pytest-python; extra == "service"
Requires-Dist: octo-pipeline-backend-setuptools-python; extra == "service"
Requires-Dist: octo-pipeline-backend-snyk-python; extra == "service"
Provides-Extra: containers
Requires-Dist: octo-pipeline-backend-docker-python; extra == "containers"
Provides-Extra: common
Requires-Dist: octo-pipeline-backend-file-python; extra == "common"
Requires-Dist: octo-pipeline-backend-gpg-python; extra == "common"
Requires-Dist: octo-pipeline-backend-tar-python; extra == "common"
Provides-Extra: source
Requires-Dist: octo-pipeline-backend-git-python; extra == "source"
Provides-Extra: go
Requires-Dist: octo-pipeline-backend-golang-python; extra == "go"
Provides-Extra: shell
Requires-Dist: octo-pipeline-backend-perl-python; extra == "shell"
Provides-Extra: tests
Requires-Dist: octo-pipeline-backend-pytest-python; extra == "tests"
Provides-Extra: data
Requires-Dist: octo-pipeline-backend-s3-python; extra == "data"
Provides-Extra: aws
Requires-Dist: octo-pipeline-backend-s3-python; extra == "aws"
